common/__init__.py
common/cutHelp.py
common/encryptHelp.py
common/excelHelp.py
common/ipHelp.py
common/jsHelp.py
common/postHelp.py
common/stringHelp.py
common/timeHelp.py
common/urlHelp.py
inputer/__init__.py
inputer/interactive_input.py
libmongo/__init__.py
libmongo/pmongo.py
libmysql/Config.py
libmysql/__init__.py
libmysql/pymysql.py
liboss/__init__.py
liboss/pyoss.py
mredis/__init__.py
mredis/weedredis.py
craw_lib_simp-1.0.0.dist-info/METADATA
craw_lib_simp-1.0.0.dist-info/WHEEL
craw_lib_simp-1.0.0.dist-info/top_level.txt
craw_lib_simp-1.0.0.dist-info/RECORD
