Metadata-Version: 2.1
Name: craw-lib-simp
Version: 1.0.0
Summary: crawler lib
Home-page: UNKNOWN
Author: UNKNOWN
Author-email: UNKNOWN
License: UNKNOWN
Keywords: crawler,lib
Platform: UNKNOWN
Classifier: Programming Language :: Python :: 3.6
Classifier: Programming Language :: Python :: 3.8
